zeroset/__init__.py
zeroset/ai0.py
zeroset/cv0.py
zeroset/log0.py
zeroset/py0.py
zeroset/s0.py
zeroset/viz0.py
zeroset-0.2.0.dist-info/METADATA
zeroset-0.2.0.dist-info/WHEEL
zeroset-0.2.0.dist-info/top_level.txt
zeroset-0.2.0.dist-info/RECORD
