Metadata-Version: 2.1
Name: zeroset
Version: 0.2.0
Summary: Useful collection of features.
Home-page: https://github.com/springkim/zeroset
Author: Bomm Kim
Author-email: springnode@gmail.com
Classifier: Programming Language :: Python :: 3
Classifier: License :: OSI Approved :: MIT License
Classifier: Operating System :: OS Independent
Requires-Python: >=3.10
Requires-Dist: natsort>=8.0.0
Requires-Dist: Pillow>=10.0.0
Requires-Dist: opencv-python
Requires-Dist: screeninfo>=0.8.0
Requires-Dist: tabulate>=0.9.0
Requires-Dist: pytz
Requires-Dist: selenium>=4.0.0
Requires-Dist: screeninfo
Requires-Dist: scikit-learn
Requires-Dist: imageio
Requires-Dist: gif
Requires-Dist: pyfftw
Requires-Dist: imagehash
Requires-Dist: tk
